{
  "generatedAt": "2026-07-17T06:54:11.289Z",
  "posts": [
    {
      "id": "mock-1",
      "title": "Monochromatic Tweed Tailoring",
      "summary": "Curate structured monochrome blazers and high-neck vests to marry Chanel structured elegance with raw Alexander McQueen styling rules. Exaggerated shoulder silhouettes remain a staple for autumn layering.",
      "source": "Vogue Runway",
      "tags": [
        "tweed",
        "monochrome",
        "bouclé"
      ],
      "imageUrl": "https://images.unsplash.com/photo-1490481651871-ab68de25d43d?q=80&w=600&auto=format&fit=crop"
    },
    {
      "id": "mock-2",
      "title": "Rebellious Leather Coordinates",
      "summary": "Incorporate heavy hardware buckles and deconstructed leather crossbody bags into loose-fitting floral slip dresses. The contrast of soft drapery against metallic, hard accents creates a powerful rebel chic look.",
      "source": "AllSaints Lookbook",
      "tags": [
        "leather",
        "grunge",
        "hardware"
      ],
      "imageUrl": "https://images.unsplash.com/photo-1509631179647-0177331693ae?q=80&w=600&auto=format&fit=crop"
    }
  ]
}